Metadata-Version: 2.1
Name: test-technologii-grudzien
Version: 0.0.4
Summary: super opis
Home-page: UNKNOWN
License: UNKNOWN
Platform: UNKNOWN
